CHANGES.md
MANIFEST.in
README.md
UNLICENSE
setup.py
src/pyramid_postmark/__init__.py
src/pyramid_postmark/hooks.py
src/pyramid_postmark.egg-info/PKG-INFO
src/pyramid_postmark.egg-info/SOURCES.txt
src/pyramid_postmark.egg-info/dependency_links.txt
src/pyramid_postmark.egg-info/not-zip-safe
src/pyramid_postmark.egg-info/requires.txt
src/pyramid_postmark.egg-info/top_level.txt
src/pyramid_postmark/fixtures/example.mako