Metadata-Version: 1.0
Name: pyramid-postmark
Version: 0.3.2
Summary: Integrate the Postmark email service with a Pyramid web application.
Home-page: http://github.com/thruflo/pyramid_postmark
Author: James Arthur
Author-email: username: thruflo, domain: gmail.com
License: This is free and unencumbered software released into the public domain.
Platform: UNKNOWN
Classifier: Development Status :: 3 - Alpha
Classifier: Environment :: Web Environment
Classifier: Intended Audience :: Developers
Classifier: License :: Public Domain
Classifier: Natural Language :: English
Classifier: Operating System :: OS Independent
Classifier: Programming Language :: Python
Classifier: Programming Language :: Python :: 2.6
Classifier: Programming Language :: Python :: 2.7
Classifier: Framework :: Pylons
Classifier: Topic :: Internet :: WWW/HTTP
Classifier: Topic :: Internet :: WWW/HTTP :: WSGI
Classifier: Topic :: Software Development :: Libraries :: Python Modules
